meta_lists/__init__.py
meta_lists/admin.py
meta_lists/admin_site.py
meta_lists/apps.py
meta_lists/list_data.py
meta_lists/models.py
meta_lists/tests.py
meta_lists/urls.py
meta_lists/views.py
meta_lists/migrations/0001_initial.py
meta_lists/migrations/0002_auto_20191026_2231.py
meta_lists/migrations/0003_auto_20191102_0033.py
meta_lists/migrations/0004_auto_20191102_1859.py
meta_lists/migrations/0005_auto_20191104_0930.py
meta_lists/migrations/__init__.py
meta_lists/tests/__init__.py
meta_lists/tests/test_lists.py
meta_lists-0.1.12.dist-info/LICENSE
meta_lists-0.1.12.dist-info/METADATA
meta_lists-0.1.12.dist-info/WHEEL
meta_lists-0.1.12.dist-info/top_level.txt
meta_lists-0.1.12.dist-info/RECORD
